[{
    "code": "ERR_APP_XXX",
    "message": "Something's wrong."
}, {
    "code": "ERR_APP_000",
    "message": "Not implemented yet."
}, {
    "code": "ERR_APP_001",
    "message": "App already started, stop the app before resolving again."
}, {
    "code": "ERR_APP_002",
    "message": "App already started, stop the app before setting up again."
}, {
    "code": "ERR_APP_003",
    "message": "App already started, stop the app before starting again."
}, {
    "code": "ERR_APP_004",
    "message": "App not started, cannot be stopped."
}, {
    "code": "ERR_APP_005",
    "message": "App not stopped, cannot be destroyed."
}, {
    "code": "ERR_APP_006",
    "message": "Cycles have been found in the dependency graph."
}, {
    "code": "ERR_APP_007",
    "message": "Module dependencies are missing in the configuration."
}, {
    "code": "ERR_MOD_000",
    "message": "Not implemented yet."
}, {
    "code": "ERR_MOD_XXX",
    "message": "Something's wrong."
}, {
    "code": "ERR_MOD_001",
    "message": "The module id must be provided."
}, {
    "code": "ERR_MOD_002",
    "message": "Options cannot be changed in module after setup."
}, {
    "code": "ERR_MOD_003",
    "message": "Dependencies cannot be changed in module after setup."
}, {
    "code": "ERR_MOD_004",
    "message": "Only an object argument is accepted as options."
}, {
    "code": "ERR_MOD_005",
    "message": "non-string argument cannot be accepted as dependencies."
}, {
    "code": "ERR_MOD_006",
    "message": "ModuleWrapper cannot be instanciated with null or missing module and app arguments."
}, {
    "code": "ERR_MOD_007",
    "message": "ModuleWrapper must be instanciated with an instance of Module."
}, {
    "code": "ERR_MOD_008",
    "message": "ModuleWrapper must be instanciated with an instance of App."
}, {
    "code": "ERR_MOD_009",
    "message": "Only an object argument is accepted as imports."
}, {
    "code": "ERR_MOD_010",
    "message": "Options cannot be changed in module wrapper after setup."
}, {
    "code": "ERR_MOD_011",
    "message": "Imports cannot be changed in module wrapper after setup."
}, {
    "code": "ERR_MOD_012",
    "message": "Only ModuleWrapper instances can be part of the object argument for imports."
}]
